{

  "Sign in" : "Sign in",
  "Phone" : "Phone",
  "Create account" : "Create an account",
  "dont have account" : "don't have an account?",
  "Name" : "Name",
  "email" : "E-mail",
  "optional" : "Optional",
  "I agree\n" : "I agree\n",
  "Next" : "Next",
  "confirm": "Confirm",
  "Dont already have an account?" : "Don't already have an account?",
  "otp" : "OTP code has been sent to your mobile phone. Resend",
  "UpdateProfile": "Update profile",
  "profileTitle": "Profile title",
  "Profile": "profile",
  "myOrders": "My Orders",
  "language": "English",
  "Privacy": "Privacy Policies",
  "Terms": "Terms and Conditions",
  "Exchange": "Exchange and refund policy",
  "Favourite": "Favourite",
  "About US": "About US",
  "About": "We are product to be the best surveillance camera installation company in jeddah",
  "Sign out": "Sign out",
  "Search Now": "Search now",
  "search": "Search",
  "Account": "Account",
  "Category": "Categories",
  "Show All": "Show All",
  "Products": "Products",
  "Shopping Cart": "Shopping cart",
  "Notifications": "Notifications",
  "the price": "the price",
  "to": "to",
  "Search results": "Search results",
  "sort by": "Sort by",
  "Order Details" : "Order details",
  "Order status": "Order status",
  "NumberItem": "Number of items",
  "DiscountCode": "Discount code",
  "Shipping": "Shipping Rate",
  "Shipping charges": "Shipping charges",
  "totalSummation": "total summation",
  "addToCart": "Add to cart",
  "productName": "Product name",
  "Product price": "Product price",
  "ProductDescription": "Product Description",
  "Read more": "Read more",
  "Hide": "Hide",
  "order number": "Order number",
  "total discount": "Total discount",
  "total items": "Total items",
  "number pieces": "the number of pieces",
  "complete order": "Complete the order",
  "payment": "Payment method",
  "payment method": "Payment when receiving",
  "Choose a title": "Choose a title",
  "Add a new address": "Add a new address",
  "Add your comments ": "Add your comments ",
  "Choose installation data": "Choose installation data",
  "Title name": "Title name",
  "Address in details": "Address in details",
  "Show location on map": "Show location on map",
  "Default Address": "Default Address",
  "Write address": "Write the address in details",
  "Choose the country": "Choose the country",
  "Deleted Successfully": "Deleted Successfully",
  "Added Successfully": "Added Successfully",
  "Please complete the data": "Please complete the data",
  "This page is empty": "This page is empty",
  "This page empty": "This page is empty",
  "Discount offers": "Discount offers",
  "settings": "Settings",
  "Best seller": "Best seller",
  "Home" : "Home",
  "Shop" : "Shopping",
  "Latest products": "Latest Product",
  "All products" : "All products",
  "Similar products" : "Similar products",
  "Product details" : "Product details",
  "Save" : "Save",
  "Choose the Categories" : "Choose the Categories",
  "Delete account": "Delete account",
  "Address": "Address",
  "City": "City",
  "District": "District",
  "Password": "Password",
  "Comments": "Comments",
  "Buy now": "Buy now",
  "Discount": "Discount ",
  "You have no notifications": "You have no notifications",
  "Discover categories": "Discover categories",
  "Welcome back": "Welcome back",
  "Forget password": "Forget password",
  "Welcome to": "Welcome to",
  "First Name": "First Name",
  "Last Name": "Last Name",
  "Confirm password": "Confirm password",
  "You have no requests yet": "You have no requests yet",
  "Orders": "Orders",
  "All orders": "All",
  "Delivered": "Delivered",
  "Review the request": "Review the request",
  "canceled": "Canceled",
  "Returns": "Returns",
  "There are no orders delivered": "There are no orders delivered",
  "There are no canceled orders": "There are no canceled orders",
  "No orders have been returned": "No orders have been returned",
  "The cart is empty": "The cart is empty",
  "total": "total",
  "discount": "discount",
  "Paying off": "Paying off",
  "Choose payment method": "Choose payment method",
  "Payment upon receipt": "Payment upon receipt",
  "Credit card": "Credit card",
  "Google": "Google",
  "Add a payment method": "Add a payment method",
  "View the order": "View the order",
  "payment methods": "payment methods",
  "Current Location": "Current Location",
  "The request has failed": "The request has failed",
  "There appears to be an error during your request": "There appears to be an error during your request",
  "Try again" : "Try again",
  "Back to home page" : "Back to home page"
}